bearshell/__init__.py
bearshell-0.1.3.dist-info/licenses/LICENSE
bearshell-0.1.3.dist-info/METADATA
bearshell-0.1.3.dist-info/WHEEL
bearshell-0.1.3.dist-info/top_level.txt
bearshell-0.1.3.dist-info/RECORD
